opttt/__init__.py
opttt/opttt.py
opttt-0.1.0.dist-info/LICENSE
opttt-0.1.0.dist-info/METADATA
opttt-0.1.0.dist-info/WHEEL
opttt-0.1.0.dist-info/top_level.txt
opttt-0.1.0.dist-info/RECORD
