Metadata-Version: 2.1
Name: opttt
Version: 0.1.0
Summary: For structured options.
Home-page: https://github.com/tshauck/opttt
Author: Trent Hauck
Author-email: trent@trenthauck.com
License: MIT license
Keywords: opttt
Platform: UNKNOWN
Classifier: Development Status :: 2 - Pre-Alpha
Classifier: Intended Audience :: Developers
Classifier: License :: OSI Approved :: MIT License
Classifier: Natural Language :: English
Classifier: Programming Language :: Python :: 3
Classifier: Programming Language :: Python :: 3.5
Classifier: Programming Language :: Python :: 3.6
Classifier: Programming Language :: Python :: 3.7
Classifier: Programming Language :: Python :: 3.8
Requires-Python: >=3.5
